openapi/__init__.py
openapi/api_client.py
openapi/api_response.py
openapi/configuration.py
openapi/exceptions.py
openapi/rest.py
openapi/api/__init__.py
openapi/api/auth_api.py
openapi/api/contracts_api.py
openapi/api/credits_api.py
openapi/api/customers_api.py
openapi/api/events_api.py
openapi/api/integrations_api.py
openapi/api/invoices_api.py
openapi/api/meters_api.py
openapi/api/plans_api.py
openapi/api/reports_api.py
openapi/api/webhooks_api.py
openapi/models/__init__.py
openapi/models/address.py
openapi/models/aggregation_method.py
openapi/models/aggregation_operator.py
openapi/models/billing_cycle_status.py
openapi/models/billing_interval.py
openapi/models/condition.py
openapi/models/contact.py
openapi/models/contract_status.py
openapi/models/create_contract_request.py
openapi/models/create_contract_response.py
openapi/models/create_customer_request.py
openapi/models/create_customer_response.py
openapi/models/create_customer_response_customer.py
openapi/models/credit_ledger_entry.py
openapi/models/criterion.py
openapi/models/criterion_operator.py
openapi/models/currency.py
openapi/models/deduct_credits_request.py
openapi/models/delete_contract_response.py
openapi/models/delete_contract_response_contract.py
openapi/models/delete_customer_response.py
openapi/models/delete_customer_response_customer.py
openapi/models/delete_event_response.py
openapi/models/delete_event_response_event.py
openapi/models/delete_meter_response.py
openapi/models/delete_meter_response_meter.py
openapi/models/delete_plan_response.py
openapi/models/delete_plan_response_plan.py
openapi/models/event.py
openapi/models/events_dry_run_request.py
openapi/models/events_dry_run_response.py
openapi/models/events_dry_run_response_object.py
openapi/models/events_dry_run_response_object_event.py
openapi/models/events_dry_run_response_object_meter_with_values_inner.py
openapi/models/filter.py
openapi/models/full_day_period.py
openapi/models/get_commitment_report_response.py
vayu_py-0.1.6.dist-info/licenses/LICENSE
vayu_py-0.1.6.dist-info/METADATA
vayu_py-0.1.6.dist-info/WHEEL
vayu_py-0.1.6.dist-info/top_level.txt
vayu_py-0.1.6.dist-info/RECORD
