Metadata-Version: 2.4
Name: vayu-py
Version: 0.1.6
Summary: The Vayu API client library in Python
Home-page: https://github.com/weft-finance/vayu-py
Author: Vayu Team
Author-email: team@withvayu.com
Requires-Python: >=3.7
License-File: LICENSE
Requires-Dist: setuptools>=42
Requires-Dist: wheel
Requires-Dist: twine
Requires-Dist: bump2version
Requires-Dist: requests
Requires-Dist: urllib3>=1.25.3
Requires-Dist: python-dateutil
Requires-Dist: pydantic
Requires-Dist: pyjwt
Dynamic: author
Dynamic: author-email
Dynamic: home-page
Dynamic: license-file
Dynamic: requires-dist
Dynamic: requires-python
Dynamic: summary
